setup.py
firedj/__init__.py
firedj/core.py
firedj.egg-info/PKG-INFO
firedj.egg-info/SOURCES.txt
firedj.egg-info/dependency_links.txt
firedj.egg-info/entry_points.txt
firedj.egg-info/not-zip-safe
firedj.egg-info/requires.txt
firedj.egg-info/top_level.txt