Metadata-Version: 1.0
Name: firedj
Version: 0.1
Summary: Django template support for Fire.app
Home-page: http://github.com/tzangms/firedj
Author: tzangms
Author-email: tzangms@gmail.com
License: BSD
Keywords: django,fire.app
Platform: UNKNOWN
Classifier: Programming Language :: Python
Classifier: Environment :: Web Environment
